django_rest_framework_nested_resource-1.1.1.dist-info/DESCRIPTION.rst
django_rest_framework_nested_resource-1.1.1.dist-info/METADATA
django_rest_framework_nested_resource-1.1.1.dist-info/metadata.json
django_rest_framework_nested_resource-1.1.1.dist-info/RECORD
django_rest_framework_nested_resource-1.1.1.dist-info/top_level.txt
django_rest_framework_nested_resource-1.1.1.dist-info/WHEEL
drf_nested_resource/__init__.py
drf_nested_resource/compat.py
drf_nested_resource/mixins.py
drf_nested_resource/models.py
drf_nested_resource/utils.py
drf_nested_resource/static/css/drf_nested_resource.css
drf_nested_resource/static/js/drf_nested_resource.js
drf_nested_resource/templates/drf_nested_resource/base.html
