Metadata-Version: 2.0
Name: django-rest-framework-nested-resource
Version: 1.1.1
Summary: DRF view mixin for nested resources
Home-page: https://github.com/simpleenergy/django-rest-framework-nested-resource
Author: SimpleEnergy
Author-email: piper@simpleenergy.com
License: BSD
Keywords: django-rest-framework-nested-resource
Platform: UNKNOWN
Classifier: Development Status :: 2 - Pre-Alpha
Classifier: Framework :: Django
Classifier: Intended Audience :: Developers
Classifier: License :: OSI Approved :: BSD License
Classifier: Natural Language :: English
Classifier: Programming Language :: Python :: 2
Classifier: Programming Language :: Python :: 2.6
Classifier: Programming Language :: Python :: 2.7
Classifier: Programming Language :: Python :: 3
Classifier: Programming Language :: Python :: 3.3
